{"event_id": "6a33ccba-fcbf-41b5-848b-b13716f1dfdc", "event_time": "2026-04-10T08:57:41.471306+00:00", "user_id": 90428, "event_type": "product_view", "device": "mobile", "country": "IN", "product_id": 1034, "price": 908.53, "ingestion_timestamp": "2026-04-10T09:28:26.358055+00:00", "processing_date": "2026-04-10"}
{"event_id": "bc28afdc-3f90-43ed-9c15-dfe94528ce5c", "event_time": "2026-04-10T08:57:41.471306+00:00", "user_id": 93872, "event_type": "add_to_cart", "device": "tablet", "country": "BR", "product_id": 1031, "price": 80.87, "ingestion_timestamp": "2026-04-10T09:28:26.358055+00:00", "processing_date": "2026-04-10"}
{"event_id": "7e927db5-e881-4a29-8e8d-bf74197ad301", "event_time": "2026-04-10T08:57:41.471306+00:00", "user_id": 26322, "event_type": "product_view", "device": "tablet", "country": "AE", "product_id": 1030, "price": 483.11, "ingestion_timestamp": "2026-04-10T09:28:26.358055+00:00", "processing_date": "2026-04-10"}
{"event_id": "0ef2ea51-07a4-48b5-9670-cf926ebd9881", "event_time": "2026-04-10T08:57:41.471306+00:00", "user_id": 8807, "event_type": "add_to_cart", "device": "mobile", "country": "AU", "product_id": 1029, "price": 958.83, "ingestion_timestamp": "2026-04-10T09:28:26.358055+00:00", "processing_date": "2026-04-10"}
{"event_id": "ea477293-472f-47fb-9bbd-c8d7770ab9c2", "event_time": "2026-04-10T08:57:41.471306+00:00", "user_id": 62355, "event_type": "product_view", "device": "mobile", "country": "FR", "product_id": 1026, "price": 826.23, "ingestion_timestamp": "2026-04-10T09:28:26.358055+00:00", "processing_date": "2026-04-10"}
{"event_id": "2aa032eb-23c5-49f3-967e-9b8b1dd510b9", "event_time": "2026-04-10T08:57:41.471306+00:00", "user_id": 30657, "event_type": "login", "device": "tablet", "country": "SG", "product_id": null, "price": null, "ingestion_timestamp": "2026-04-10T09:28:26.358055+00:00", "processing_date": "2026-04-10"}
{"event_id": "6d9e25e4-7c9d-4621-86b9-c8b42fbad33d", "event_time": "2026-04-10T08:57:41.471306+00:00", "user_id": 81975, "event_type": "purchase", "device": "desktop", "country": "JP", "product_id": 1050, "price": 146.65, "ingestion_timestamp": "2026-04-10T09:28:26.358055+00:00", "processing_date": "2026-04-10"}
{"event_id": "887aa710-f0f6-4ec3-81bc-a2f405f508d5", "event_time": "2026-04-10T08:57:41.471306+00:00", "user_id": 82952, "event_type": "product_view", "device": "desktop", "country": "GB", "product_id": 1039, "price": 254.35, "ingestion_timestamp": "2026-04-10T09:28:26.358055+00:00", "processing_date": "2026-04-10"}
{"event_id": "a54833ab-a962-4c0e-bac4-c027ee7ce6d6", "event_time": "2026-04-10T08:57:41.471306+00:00", "user_id": 59188, "event_type": "product_view", "device": "tablet", "country": "JP", "product_id": 1006, "price": 681.28, "ingestion_timestamp": "2026-04-10T09:28:26.358055+00:00", "processing_date": "2026-04-10"}
{"event_id": "bb1a5325-3ea0-4a89-957c-fdba6a10e26f", "event_time": "2026-04-10T08:57:41.471306+00:00", "user_id": 13291, "event_type": "add_to_cart", "device": "tablet", "country": "SG", "product_id": 1028, "price": 101.28, "ingestion_timestamp": "2026-04-10T09:28:26.358055+00:00", "processing_date": "2026-04-10"}
{"event_id": "76618ea7-c3a6-4e1a-8530-69483c3afb1d", "event_time": "2026-04-10T08:57:41.471949+00:00", "user_id": 33936, "event_type": "add_to_cart", "device": "desktop", "country": "JP", "product_id": 1035, "price": 428.32, "ingestion_timestamp": "2026-04-10T09:28:26.358055+00:00", "processing_date": "2026-04-10"}
{"event_id": "c4b341bd-515d-40fd-8dc2-e0305f8c8c9e", "event_time": "2026-04-10T08:57:41.471949+00:00", "user_id": 53958, "event_type": "product_view", "device": "desktop", "country": "CA", "product_id": 1040, "price": 555.99, "ingestion_timestamp": "2026-04-10T09:28:26.358055+00:00", "processing_date": "2026-04-10"}
{"event_id": "893e0ce7-bfcf-4934-bc07-c2a5e60372f0", "event_time": "2026-04-10T08:57:41.471949+00:00", "user_id": 29171, "event_type": "product_view", "device": "mobile", "country": "FR", "product_id": 1024, "price": 113.34, "ingestion_timestamp": "2026-04-10T09:28:26.358055+00:00", "processing_date": "2026-04-10"}
{"event_id": "0f6f0517-ccfc-4ef8-a5ed-2b6421608405", "event_time": "2026-04-10T08:57:41.471949+00:00", "user_id": 62889, "event_type": "product_view", "device": "mobile", "country": "KR", "product_id": 1005, "price": 39.59, "ingestion_timestamp": "2026-04-10T09:28:26.358055+00:00", "processing_date": "2026-04-10"}
{"event_id": "b23e24e1-6588-4610-b204-d9f82b9a7aa3", "event_time": "2026-04-10T08:57:41.471949+00:00", "user_id": 45716, "event_type": "login", "device": "desktop", "country": "KR", "product_id": null, "price": null, "ingestion_timestamp": "2026-04-10T09:28:26.358055+00:00", "processing_date": "2026-04-10"}
{"event_id": "1216cba7-84b2-4f74-98e1-afa0426a8834", "event_time": "2026-04-10T08:57:41.471949+00:00", "user_id": 59092, "event_type": "purchase", "device": "mobile", "country": "DE", "product_id": 1029, "price": 759.55, "ingestion_timestamp": "2026-04-10T09:28:26.358055+00:00", "processing_date": "2026-04-10"}
{"event_id": "c19c48c9-da75-4366-b182-0a39da152f38", "event_time": "2026-04-10T08:57:41.471949+00:00", "user_id": 28939, "event_type": "add_to_cart", "device": "desktop", "country": "JP", "product_id": 1021, "price": 584.71, "ingestion_timestamp": "2026-04-10T09:28:26.358055+00:00", "processing_date": "2026-04-10"}
{"event_id": "40265919-8c77-4448-83a8-949659e5e140", "event_time": "2026-04-10T08:57:41.471949+00:00", "user_id": 44926, "event_type": "product_view", "device": "desktop", "country": "US", "product_id": 1022, "price": 552.48, "ingestion_timestamp": "2026-04-10T09:28:26.358055+00:00", "processing_date": "2026-04-10"}
{"event_id": "c3fc7291-7502-445b-8e09-fd649d4a0230", "event_time": "2026-04-10T08:57:41.471949+00:00", "user_id": 35536, "event_type": "purchase", "device": "tablet", "country": "AU", "product_id": 1047, "price": 188.93, "ingestion_timestamp": "2026-04-10T09:28:26.358055+00:00", "processing_date": "2026-04-10"}
{"event_id": "95df40f0-a336-4f08-bc8a-c7d53b1b9d51", "event_time": "2026-04-10T08:57:41.471949+00:00", "user_id": 79181, "event_type": "product_view", "device": "mobile", "country": "JP", "product_id": 1013, "price": 299.68, "ingestion_timestamp": "2026-04-10T09:28:26.358055+00:00", "processing_date": "2026-04-10"}
{"event_id": "e414bf9e-379a-42a3-b4d6-349db53b021f", "event_time": "2026-04-10T08:57:41.471949+00:00", "user_id": 30511, "event_type": "login", "device": "mobile", "country": "IN", "product_id": null, "price": null, "ingestion_timestamp": "2026-04-10T09:28:26.358055+00:00", "processing_date": "2026-04-10"}
{"event_id": "9348a2e3-5b6c-4086-95ed-6fd252da08b1", "event_time": "2026-04-10T08:57:41.471949+00:00", "user_id": 16907, "event_type": "product_view", "device": "desktop", "country": "JP", "product_id": 1038, "price": 106.64, "ingestion_timestamp": "2026-04-10T09:28:26.358055+00:00", "processing_date": "2026-04-10"}
{"event_id": "2f719841-d3ac-4be6-9158-db6c08072ce2", "event_time": "2026-04-10T08:57:41.471949+00:00", "user_id": 86403, "event_type": "add_to_cart", "device": "mobile", "country": "KR", "product_id": 1007, "price": 60.61, "ingestion_timestamp": "2026-04-10T09:28:26.358055+00:00", "processing_date": "2026-04-10"}
{"event_id": "0c9b10c3-e636-4e0a-b265-e7de4e5d89fb", "event_time": "2026-04-10T08:57:41.471949+00:00", "user_id": 47325, "event_type": "product_view", "device": "mobile", "country": "AU", "product_id": 1043, "price": 27.88, "ingestion_timestamp": "2026-04-10T09:28:26.358055+00:00", "processing_date": "2026-04-10"}
{"event_id": "2ad791c4-123b-4d9f-a3cc-abbfd4859494", "event_time": "2026-04-10T08:57:43.968956+00:00", "user_id": 26060, "event_type": "product_view", "device": "tablet", "country": "US", "product_id": 1043, "price": 63.89, "ingestion_timestamp": "2026-04-10T09:28:26.358055+00:00", "processing_date": "2026-04-10"}
{"event_id": "36a41859-0ce5-472b-9dc3-9d98addacea6", "event_time": "2026-04-10T08:57:43.968956+00:00", "user_id": 6886, "event_type": "product_view", "device": "mobile", "country": "AE", "product_id": 1036, "price": 143.73, "ingestion_timestamp": "2026-04-10T09:28:26.358055+00:00", "processing_date": "2026-04-10"}
{"event_id": "2d8d94d2-795a-4bee-b5f0-371f5ab5b0f4", "event_time": "2026-04-10T08:57:43.968956+00:00", "user_id": 29482, "event_type": "product_view", "device": "tablet", "country": "FR", "product_id": 1031, "price": 733.76, "ingestion_timestamp": "2026-04-10T09:28:26.358055+00:00", "processing_date": "2026-04-10"}
{"event_id": "1e760852-dceb-4794-b2a4-c6e6e66c218c", "event_time": "2026-04-10T08:57:43.968956+00:00", "user_id": 96322, "event_type": "purchase", "device": "mobile", "country": "SG", "product_id": 1030, "price": 141.76, "ingestion_timestamp": "2026-04-10T09:28:26.358055+00:00", "processing_date": "2026-04-10"}
{"event_id": "382eaa5b-3222-4035-ae3e-31e950650c5c", "event_time": "2026-04-10T08:57:43.968956+00:00", "user_id": 79654, "event_type": "product_view", "device": "tablet", "country": "AU", "product_id": 1046, "price": 128.91, "ingestion_timestamp": "2026-04-10T09:28:26.358055+00:00", "processing_date": "2026-04-10"}
{"event_id": "7e601250-8a44-4827-a3d3-6f8c77a6a0e8", "event_time": "2026-04-10T08:57:43.968956+00:00", "user_id": 8944, "event_type": "product_view", "device": "desktop", "country": "US", "product_id": 1006, "price": 348.75, "ingestion_timestamp": "2026-04-10T09:28:26.358055+00:00", "processing_date": "2026-04-10"}
{"event_id": "5e6505d1-448f-408d-b9b1-4392f59530f1", "event_time": "2026-04-10T08:57:43.968956+00:00", "user_id": 94832, "event_type": "add_to_cart", "device": "mobile", "country": "AU", "product_id": 1026, "price": 395.41, "ingestion_timestamp": "2026-04-10T09:28:26.358055+00:00", "processing_date": "2026-04-10"}
{"event_id": "2ebc05d1-1a6f-411d-bae1-4580b20bbc07", "event_time": "2026-04-10T08:57:43.968956+00:00", "user_id": 61826, "event_type": "product_view", "device": "tablet", "country": "KR", "product_id": 1028, "price": 436.03, "ingestion_timestamp": "2026-04-10T09:28:26.358055+00:00", "processing_date": "2026-04-10"}
{"event_id": "d02f1b65-b76e-4b32-bbdb-3ffcb34b1ca7", "event_time": "2026-04-10T08:57:43.968956+00:00", "user_id": 76839, "event_type": "product_view", "device": "desktop", "country": "BR", "product_id": 1049, "price": 780.92, "ingestion_timestamp": "2026-04-10T09:28:26.358055+00:00", "processing_date": "2026-04-10"}
{"event_id": "bf9f0b28-a942-48e8-b641-8340eb32b1dc", "event_time": "2026-04-10T08:57:43.968956+00:00", "user_id": 23443, "event_type": "add_to_cart", "device": "tablet", "country": "JP", "product_id": 1050, "price": 438.04, "ingestion_timestamp": "2026-04-10T09:28:26.358055+00:00", "processing_date": "2026-04-10"}
{"event_id": "e58085f5-5805-4d7a-b9d5-41bdc4335464", "event_time": "2026-04-10T08:57:43.968956+00:00", "user_id": 56230, "event_type": "product_view", "device": "mobile", "country": "KR", "product_id": 1004, "price": 320.04, "ingestion_timestamp": "2026-04-10T09:28:26.358055+00:00", "processing_date": "2026-04-10"}
{"event_id": "49a71f7e-de5e-4c3a-bfda-dc63981882f3", "event_time": "2026-04-10T08:57:43.968956+00:00", "user_id": 35719, "event_type": "product_view", "device": "desktop", "country": "GB", "product_id": 1036, "price": 952.42, "ingestion_timestamp": "2026-04-10T09:28:26.358055+00:00", "processing_date": "2026-04-10"}
{"event_id": "46b9b524-3add-4445-a539-64782256ba5a", "event_time": "2026-04-10T08:57:43.968956+00:00", "user_id": 93302, "event_type": "product_view", "device": "mobile", "country": "CA", "product_id": 1008, "price": 237.89, "ingestion_timestamp": "2026-04-10T09:28:26.358055+00:00", "processing_date": "2026-04-10"}
{"event_id": "4e27f6f3-28de-4d7f-9a51-029a979f35e6", "event_time": "2026-04-10T08:57:43.968956+00:00", "user_id": 6703, "event_type": "product_view", "device": "mobile", "country": "CA", "product_id": 1030, "price": 675.9, "ingestion_timestamp": "2026-04-10T09:28:26.358055+00:00", "processing_date": "2026-04-10"}
{"event_id": "5e8d94b8-4be7-42d5-8381-9b2295f9322d", "event_time": "2026-04-10T08:57:43.968956+00:00", "user_id": 15257, "event_type": "add_to_cart", "device": "desktop", "country": "AU", "product_id": 1026, "price": 927.25, "ingestion_timestamp": "2026-04-10T09:28:26.358055+00:00", "processing_date": "2026-04-10"}
{"event_id": "88975853-86af-4fd9-8f90-8dc374548af3", "event_time": "2026-04-10T08:57:43.968956+00:00", "user_id": 26670, "event_type": "product_view", "device": "desktop", "country": "JP", "product_id": 1011, "price": 867.5, "ingestion_timestamp": "2026-04-10T09:28:26.358055+00:00", "processing_date": "2026-04-10"}
{"event_id": "b3dd1ed2-4247-46c4-8ee0-8148c543aa3b", "event_time": "2026-04-10T08:57:43.968956+00:00", "user_id": 16984, "event_type": "add_to_cart", "device": "mobile", "country": "US", "product_id": 1032, "price": 921.08, "ingestion_timestamp": "2026-04-10T09:28:26.358055+00:00", "processing_date": "2026-04-10"}
{"event_id": "64b9071a-2456-48c1-a187-278bc3f3ae01", "event_time": "2026-04-10T08:57:43.968956+00:00", "user_id": 63519, "event_type": "product_view", "device": "mobile", "country": "AU", "product_id": 1039, "price": 943.23, "ingestion_timestamp": "2026-04-10T09:28:26.358055+00:00", "processing_date": "2026-04-10"}
{"event_id": "67355405-9d80-41e1-affb-716b7eccf0e9", "event_time": "2026-04-10T08:57:43.968956+00:00", "user_id": 36245, "event_type": "add_to_cart", "device": "mobile", "country": "US", "product_id": 1050, "price": 544.55, "ingestion_timestamp": "2026-04-10T09:28:26.358055+00:00", "processing_date": "2026-04-10"}
{"event_id": "2bb86d94-b7a3-4d61-a24a-56e59ba059e3", "event_time": "2026-04-10T08:57:43.968956+00:00", "user_id": 57031, "event_type": "product_view", "device": "desktop", "country": "IN", "product_id": 1032, "price": 94.34, "ingestion_timestamp": "2026-04-10T09:28:26.358055+00:00", "processing_date": "2026-04-10"}
{"event_id": "31727618-3fd6-4be2-928a-be903adbf3b8", "event_time": "2026-04-10T08:57:43.968956+00:00", "user_id": 36963, "event_type": "product_view", "device": "mobile", "country": "AU", "product_id": 1032, "price": 509.21, "ingestion_timestamp": "2026-04-10T09:28:26.358055+00:00", "processing_date": "2026-04-10"}
{"event_id": "72ab2595-6027-4930-96aa-84489a04b2d6", "event_time": "2026-04-10T08:57:43.969639+00:00", "user_id": 17657, "event_type": "logout", "device": "desktop", "country": "KR", "product_id": null, "price": null, "ingestion_timestamp": "2026-04-10T09:28:26.358055+00:00", "processing_date": "2026-04-10"}
{"event_id": "936ba956-0981-4aaa-ad2c-05850bf925ce", "event_time": "2026-04-10T08:57:43.969639+00:00", "user_id": 71251, "event_type": "product_view", "device": "mobile", "country": "FR", "product_id": 1013, "price": 666.41, "ingestion_timestamp": "2026-04-10T09:28:26.358055+00:00", "processing_date": "2026-04-10"}
{"event_id": "58ecf8f7-639a-4fea-8d97-d15daf7b7463", "event_time": "2026-04-10T08:57:43.969639+00:00", "user_id": 84565, "event_type": "product_view", "device": "tablet", "country": "SG", "product_id": 1021, "price": 80.75, "ingestion_timestamp": "2026-04-10T09:28:26.358055+00:00", "processing_date": "2026-04-10"}
{"event_id": "4508828e-0790-47d5-b90f-d607cc00556c", "event_time": "2026-04-10T08:57:43.969639+00:00", "user_id": 90976, "event_type": "product_view", "device": "mobile", "country": "IN", "product_id": 1032, "price": 66.36, "ingestion_timestamp": "2026-04-10T09:28:26.358055+00:00", "processing_date": "2026-04-10"}
{"event_id": "99035732-5750-45f5-a793-9e0669230921", "event_time": "2026-04-10T08:57:46.471835+00:00", "user_id": 3899, "event_type": "product_view", "device": "tablet", "country": "DE", "product_id": 1026, "price": 437.21, "ingestion_timestamp": "2026-04-10T09:28:26.358055+00:00", "processing_date": "2026-04-10"}
{"event_id": "bdce2fc8-8673-4d31-99f3-52e536086a58", "event_time": "2026-04-10T08:57:46.471835+00:00", "user_id": 61666, "event_type": "product_view", "device": "mobile", "country": "AU", "product_id": 1046, "price": 858.44, "ingestion_timestamp": "2026-04-10T09:28:26.358055+00:00", "processing_date": "2026-04-10"}
{"event_id": "277ebcde-bd1c-4914-96f0-0eade86e1b56", "event_time": "2026-04-10T08:57:46.471835+00:00", "user_id": 88836, "event_type": "product_view", "device": "mobile", "country": "US", "product_id": 1042, "price": 702.35, "ingestion_timestamp": "2026-04-10T09:28:26.358055+00:00", "processing_date": "2026-04-10"}
{"event_id": "43599f65-5380-4cf7-bef9-810bfdbe90e4", "event_time": "2026-04-10T08:57:46.471835+00:00", "user_id": 93989, "event_type": "login", "device": "mobile", "country": "IN", "product_id": null, "price": null, "ingestion_timestamp": "2026-04-10T09:28:26.358055+00:00", "processing_date": "2026-04-10"}
{"event_id": "e669a39a-426b-4e30-aebf-8c027e575443", "event_time": "2026-04-10T08:57:46.471835+00:00", "user_id": 68463, "event_type": "add_to_cart", "device": "mobile", "country": "DE", "product_id": 1044, "price": 705.47, "ingestion_timestamp": "2026-04-10T09:28:26.358055+00:00", "processing_date": "2026-04-10"}
{"event_id": "008e48d9-c11b-49f3-aac2-379afe6ad250", "event_time": "2026-04-10T08:57:46.471835+00:00", "user_id": 37150, "event_type": "product_view", "device": "mobile", "country": "AU", "product_id": 1030, "price": 72.32, "ingestion_timestamp": "2026-04-10T09:28:26.358055+00:00", "processing_date": "2026-04-10"}
{"event_id": "ca2ea4fd-f579-4d38-a015-b0322f1d825a", "event_time": "2026-04-10T08:57:46.472446+00:00", "user_id": 13399, "event_type": "product_view", "device": "mobile", "country": "BR", "product_id": 1044, "price": 621.46, "ingestion_timestamp": "2026-04-10T09:28:26.358055+00:00", "processing_date": "2026-04-10"}
{"event_id": "c0809b03-07e8-418e-9760-035c50536076", "event_time": "2026-04-10T08:57:46.472446+00:00", "user_id": 45078, "event_type": "add_to_cart", "device": "mobile", "country": "BR", "product_id": 1034, "price": 22.94, "ingestion_timestamp": "2026-04-10T09:28:26.358055+00:00", "processing_date": "2026-04-10"}
{"event_id": "88f08587-99f0-4916-8295-99615c18feac", "event_time": "2026-04-10T08:57:46.472960+00:00", "user_id": 43634, "event_type": "add_to_cart", "device": "mobile", "country": "CA", "product_id": 1037, "price": 352.95, "ingestion_timestamp": "2026-04-10T09:28:26.358055+00:00", "processing_date": "2026-04-10"}
{"event_id": "8034f06a-ec64-412d-8fd9-e55a66ec77f6", "event_time": "2026-04-10T08:57:46.472960+00:00", "user_id": 21988, "event_type": "product_view", "device": "desktop", "country": "SG", "product_id": 1007, "price": 288.09, "ingestion_timestamp": "2026-04-10T09:28:26.358055+00:00", "processing_date": "2026-04-10"}
{"event_id": "85b639cd-9b2b-4346-b95e-e21a0af63ae3", "event_time": "2026-04-10T08:57:46.472960+00:00", "user_id": 34689, "event_type": "login", "device": "desktop", "country": "DE", "product_id": null, "price": null, "ingestion_timestamp": "2026-04-10T09:28:26.358055+00:00", "processing_date": "2026-04-10"}
{"event_id": "07197739-7d76-4476-9878-f2010dff514e", "event_time": "2026-04-10T08:57:46.472960+00:00", "user_id": 85680, "event_type": "product_view", "device": "desktop", "country": "SG", "product_id": 1022, "price": 19.55, "ingestion_timestamp": "2026-04-10T09:28:26.358055+00:00", "processing_date": "2026-04-10"}
{"event_id": "28254b0d-f8d6-495b-923c-a58e5b6ac923", "event_time": "2026-04-10T08:57:46.472960+00:00", "user_id": 4990, "event_type": "product_view", "device": "mobile", "country": "SG", "product_id": 1040, "price": 809.3, "ingestion_timestamp": "2026-04-10T09:28:26.358055+00:00", "processing_date": "2026-04-10"}
{"event_id": "267a6412-c70c-4c98-a376-bc056a767a14", "event_time": "2026-04-10T08:57:46.472960+00:00", "user_id": 9135, "event_type": "product_view", "device": "mobile", "country": "BR", "product_id": 1030, "price": 841.55, "ingestion_timestamp": "2026-04-10T09:28:26.358055+00:00", "processing_date": "2026-04-10"}
{"event_id": "e1c67fa1-e75a-4e98-af69-5d1974652bac", "event_time": "2026-04-10T08:57:46.472960+00:00", "user_id": 41920, "event_type": "product_view", "device": "mobile", "country": "US", "product_id": 1001, "price": 534.93, "ingestion_timestamp": "2026-04-10T09:28:26.358055+00:00", "processing_date": "2026-04-10"}
{"event_id": "8bb52447-ef07-4b55-8314-bbc3a7105945", "event_time": "2026-04-10T08:57:46.472960+00:00", "user_id": 38188, "event_type": "product_view", "device": "mobile", "country": "KR", "product_id": 1025, "price": 836.47, "ingestion_timestamp": "2026-04-10T09:28:26.358055+00:00", "processing_date": "2026-04-10"}
{"event_id": "96c59db9-0e88-4a84-9b6d-7f30b2eed44c", "event_time": "2026-04-10T08:57:46.473472+00:00", "user_id": 20520, "event_type": "product_view", "device": "mobile", "country": "IN", "product_id": 1038, "price": 746.43, "ingestion_timestamp": "2026-04-10T09:28:26.358055+00:00", "processing_date": "2026-04-10"}
{"event_id": "20d5e05b-7c16-4bca-883c-864520a72d72", "event_time": "2026-04-10T08:57:46.473472+00:00", "user_id": 18871, "event_type": "product_view", "device": "desktop", "country": "GB", "product_id": 1001, "price": 561.98, "ingestion_timestamp": "2026-04-10T09:28:26.358055+00:00", "processing_date": "2026-04-10"}
{"event_id": "bb6b516f-9007-4278-bdc9-c5a5c3e4575c", "event_time": "2026-04-10T08:57:46.473472+00:00", "user_id": 84922, "event_type": "add_to_cart", "device": "desktop", "country": "SG", "product_id": 1018, "price": 775.78, "ingestion_timestamp": "2026-04-10T09:28:26.358055+00:00", "processing_date": "2026-04-10"}
{"event_id": "dae5b21b-1e70-4b54-bbac-f6bb57bdf8e4", "event_time": "2026-04-10T08:57:46.473472+00:00", "user_id": 96879, "event_type": "add_to_cart", "device": "mobile", "country": "CA", "product_id": 1021, "price": 622.95, "ingestion_timestamp": "2026-04-10T09:28:26.358055+00:00", "processing_date": "2026-04-10"}
{"event_id": "2cdd3b9f-59b9-45de-9e43-2bbd68b94bbe", "event_time": "2026-04-10T08:57:46.473472+00:00", "user_id": 335, "event_type": "product_view", "device": "mobile", "country": "FR", "product_id": 1031, "price": 406.92, "ingestion_timestamp": "2026-04-10T09:28:26.358055+00:00", "processing_date": "2026-04-10"}
{"event_id": "0e796233-7bf7-4554-a07e-e11c97c814de", "event_time": "2026-04-10T08:57:46.473472+00:00", "user_id": 66047, "event_type": "product_view", "device": "desktop", "country": "IN", "product_id": 1045, "price": 792.2, "ingestion_timestamp": "2026-04-10T09:28:26.358055+00:00", "processing_date": "2026-04-10"}
{"event_id": "0fa96b26-faf8-48e4-bde5-a02af546d465", "event_time": "2026-04-10T08:57:46.473472+00:00", "user_id": 8440, "event_type": "product_view", "device": "tablet", "country": "US", "product_id": 1010, "price": 871.61, "ingestion_timestamp": "2026-04-10T09:28:26.358055+00:00", "processing_date": "2026-04-10"}
{"event_id": "94b5e003-a834-4d7d-b8c9-e90f19fbd99f", "event_time": "2026-04-10T08:57:48.980450+00:00", "user_id": 85773, "event_type": "product_view", "device": "desktop", "country": "JP", "product_id": 1012, "price": 741.45, "ingestion_timestamp": "2026-04-10T09:28:26.358055+00:00", "processing_date": "2026-04-10"}
{"event_id": "ce50b112-479d-455c-9e49-34704650c36d", "event_time": "2026-04-10T08:57:48.980450+00:00", "user_id": 66390, "event_type": "product_view", "device": "mobile", "country": "SG", "product_id": 1014, "price": 15.17, "ingestion_timestamp": "2026-04-10T09:28:26.358055+00:00", "processing_date": "2026-04-10"}
{"event_id": "9394ecde-b1cc-4c1e-88a6-de8e9fd67953", "event_time": "2026-04-10T08:57:48.980450+00:00", "user_id": 97675, "event_type": "logout", "device": "desktop", "country": "JP", "product_id": null, "price": null, "ingestion_timestamp": "2026-04-10T09:28:26.358055+00:00", "processing_date": "2026-04-10"}
{"event_id": "0dadee9c-8aad-45f2-9a4c-351f25de08b4", "event_time": "2026-04-10T08:57:48.980450+00:00", "user_id": 7662, "event_type": "product_view", "device": "desktop", "country": "SG", "product_id": 1005, "price": 762.41, "ingestion_timestamp": "2026-04-10T09:28:26.358055+00:00", "processing_date": "2026-04-10"}
{"event_id": "645bd2a5-05c7-4b2c-a1e0-3fdf2e40f4a1", "event_time": "2026-04-10T08:57:48.980450+00:00", "user_id": 85645, "event_type": "add_to_cart", "device": "mobile", "country": "BR", "product_id": 1003, "price": 87.94, "ingestion_timestamp": "2026-04-10T09:28:26.358055+00:00", "processing_date": "2026-04-10"}
{"event_id": "a67865a0-cd0b-4608-922c-5d7a25647281", "event_time": "2026-04-10T08:57:48.980450+00:00", "user_id": 83278, "event_type": "product_view", "device": "mobile", "country": "KR", "product_id": 1026, "price": 946.67, "ingestion_timestamp": "2026-04-10T09:28:26.358055+00:00", "processing_date": "2026-04-10"}
{"event_id": "19e5462a-7925-4d65-ad1f-38e055718cc3", "event_time": "2026-04-10T08:57:48.980450+00:00", "user_id": 9336, "event_type": "purchase", "device": "mobile", "country": "BR", "product_id": 1050, "price": 246.25, "ingestion_timestamp": "2026-04-10T09:28:26.358055+00:00", "processing_date": "2026-04-10"}
{"event_id": "bcd9ee44-ea41-4f80-baf0-f3a1f120f705", "event_time": "2026-04-10T08:57:48.980450+00:00", "user_id": 60622, "event_type": "login", "device": "tablet", "country": "SG", "product_id": null, "price": null, "ingestion_timestamp": "2026-04-10T09:28:26.358055+00:00", "processing_date": "2026-04-10"}
{"event_id": "2fc214c7-bcea-4ee7-b917-c0bc434dc140", "event_time": "2026-04-10T08:57:48.980450+00:00", "user_id": 16854, "event_type": "product_view", "device": "tablet", "country": "FR", "product_id": 1050, "price": 536.82, "ingestion_timestamp": "2026-04-10T09:28:26.358055+00:00", "processing_date": "2026-04-10"}
{"event_id": "051fe035-6b51-4d60-abc4-e0ffaa855e78", "event_time": "2026-04-10T08:57:48.980450+00:00", "user_id": 90531, "event_type": "product_view", "device": "mobile", "country": "AE", "product_id": 1019, "price": 849.48, "ingestion_timestamp": "2026-04-10T09:28:26.358055+00:00", "processing_date": "2026-04-10"}
{"event_id": "62c6e877-cd9b-452c-a6fb-7c84d367b594", "event_time": "2026-04-10T08:57:48.980450+00:00", "user_id": 67089, "event_type": "product_view", "device": "mobile", "country": "CA", "product_id": 1048, "price": 720.86, "ingestion_timestamp": "2026-04-10T09:28:26.358055+00:00", "processing_date": "2026-04-10"}
{"event_id": "ddfdacd6-159b-4109-b664-fc6d1ea74326", "event_time": "2026-04-10T08:57:48.980450+00:00", "user_id": 62565, "event_type": "purchase", "device": "desktop", "country": "BR", "product_id": 1001, "price": 300.14, "ingestion_timestamp": "2026-04-10T09:28:26.358055+00:00", "processing_date": "2026-04-10"}
{"event_id": "9f162bd4-cd87-43a4-bfcf-c27960f7e4f1", "event_time": "2026-04-10T08:57:48.980450+00:00", "user_id": 19917, "event_type": "purchase", "device": "mobile", "country": "CA", "product_id": 1033, "price": 157.47, "ingestion_timestamp": "2026-04-10T09:28:26.358055+00:00", "processing_date": "2026-04-10"}
{"event_id": "2c8ef332-bea3-48fc-82cd-35379c64265b", "event_time": "2026-04-10T08:57:48.980450+00:00", "user_id": 31353, "event_type": "purchase", "device": "desktop", "country": "US", "product_id": 1008, "price": 310.36, "ingestion_timestamp": "2026-04-10T09:28:26.358055+00:00", "processing_date": "2026-04-10"}
{"event_id": "f4112ebb-e8df-4db2-bcb5-e303ef40dc50", "event_time": "2026-04-10T08:57:48.980450+00:00", "user_id": 78473, "event_type": "product_view", "device": "desktop", "country": "IN", "product_id": 1016, "price": 858.47, "ingestion_timestamp": "2026-04-10T09:28:26.358055+00:00", "processing_date": "2026-04-10"}
{"event_id": "8ddf29fe-096e-4ebb-b125-5d64b8b65551", "event_time": "2026-04-10T08:57:48.980450+00:00", "user_id": 63666, "event_type": "product_view", "device": "tablet", "country": "BR", "product_id": 1014, "price": 939.77, "ingestion_timestamp": "2026-04-10T09:28:26.358055+00:00", "processing_date": "2026-04-10"}
{"event_id": "823390e1-1d0e-4291-9be7-7a851b4e6351", "event_time": "2026-04-10T08:57:48.980450+00:00", "user_id": 17415, "event_type": "product_view", "device": "mobile", "country": "DE", "product_id": 1045, "price": 819.52, "ingestion_timestamp": "2026-04-10T09:28:26.358055+00:00", "processing_date": "2026-04-10"}
{"event_id": "92ab2c70-1f10-4ad7-9287-d4ae56414acc", "event_time": "2026-04-10T08:57:48.980450+00:00", "user_id": 40094, "event_type": "add_to_cart", "device": "desktop", "country": "FR", "product_id": 1027, "price": 392.81, "ingestion_timestamp": "2026-04-10T09:28:26.358055+00:00", "processing_date": "2026-04-10"}
{"event_id": "fa33301d-1e1f-46a9-8383-809a07855b77", "event_time": "2026-04-10T08:57:48.980450+00:00", "user_id": 74287, "event_type": "purchase", "device": "tablet", "country": "IN", "product_id": 1022, "price": 739.33, "ingestion_timestamp": "2026-04-10T09:28:26.358055+00:00", "processing_date": "2026-04-10"}
{"event_id": "f7d1795c-758b-48b6-8eda-75d8703247f1", "event_time": "2026-04-10T08:57:48.980450+00:00", "user_id": 6772, "event_type": "add_to_cart", "device": "mobile", "country": "GB", "product_id": 1004, "price": 418.51, "ingestion_timestamp": "2026-04-10T09:28:26.358055+00:00", "processing_date": "2026-04-10"}
{"event_id": "e536bf7c-0aa8-48ec-b47b-aa9015ce388a", "event_time": "2026-04-10T08:57:48.980450+00:00", "user_id": 85876, "event_type": "product_view", "device": "tablet", "country": "CA", "product_id": 1014, "price": 583.17, "ingestion_timestamp": "2026-04-10T09:28:26.358055+00:00", "processing_date": "2026-04-10"}
{"event_id": "d114deef-5285-4270-88de-22c8b3c15d04", "event_time": "2026-04-10T08:57:48.980450+00:00", "user_id": 65412, "event_type": "product_view", "device": "mobile", "country": "BR", "product_id": 1042, "price": 406.09, "ingestion_timestamp": "2026-04-10T09:28:26.358055+00:00", "processing_date": "2026-04-10"}
{"event_id": "1818e4a2-5e8e-4bc3-9ecc-a580fd306701", "event_time": "2026-04-10T08:57:48.980450+00:00", "user_id": 83854, "event_type": "product_view", "device": "mobile", "country": "US", "product_id": 1046, "price": 966.8, "ingestion_timestamp": "2026-04-10T09:28:26.358055+00:00", "processing_date": "2026-04-10"}
{"event_id": "4d175ec9-cbfd-4f42-a951-4e4fb83e807d", "event_time": "2026-04-10T08:57:48.980450+00:00", "user_id": 21065, "event_type": "purchase", "device": "desktop", "country": "SG", "product_id": 1045, "price": 656.5, "ingestion_timestamp": "2026-04-10T09:28:26.358055+00:00", "processing_date": "2026-04-10"}
{"event_id": "30962c76-40d1-4a17-9cff-16daa6a3ad76", "event_time": "2026-04-10T08:57:48.980450+00:00", "user_id": 10292, "event_type": "logout", "device": "desktop", "country": "BR", "product_id": null, "price": null, "ingestion_timestamp": "2026-04-10T09:28:26.358055+00:00", "processing_date": "2026-04-10"}